horsebox/__init__.py
horsebox/main.py
horsebox/cli/__init__.py
horsebox/cli/combined_option.py
horsebox/cli/config.py
horsebox/cli/param_parser.py
horsebox/cli/render.py
horsebox/collectors/__init__.py
horsebox/collectors/collector_guess.py
horsebox/collectors/factory.py
horsebox/collectors/pattern.py
horsebox/collectors/collector_fs/__init__.py
horsebox/collectors/collector_fs/collector.py
horsebox/collectors/collector_fs/fs_by_content.py
horsebox/collectors/collector_fs/fs_by_filename.py
horsebox/collectors/collector_fs/fs_by_line.py
horsebox/collectors/collector_html/__init__.py
horsebox/collectors/collector_html/html.py
horsebox/collectors/collector_pdf/__init__.py
horsebox/collectors/collector_pdf/pdf.py
horsebox/collectors/collector_raw/__init__.py
horsebox/collectors/collector_raw/raw.py
horsebox/collectors/collector_rss/__init__.py
horsebox/collectors/collector_rss/rss.py
horsebox/collectors/guessers/__init__.py
horsebox/collectors/guessers/html.py
horsebox/collectors/guessers/pdf.py
horsebox/collectors/guessers/raw.py
horsebox/collectors/guessers/rss.py
horsebox/commands/__init__.py
horsebox/commands/analyze.py
horsebox/commands/build.py
horsebox/commands/config.py
horsebox/commands/inspect.py
horsebox/commands/refresh.py
horsebox/commands/schema.py
horsebox/commands/search.py
horsebox/formatters/__init__.py
horsebox/formatters/json.py
horsebox/formatters/text.py
horsebox/indexer/__init__.py
horsebox/indexer/build_args.py
horsebox/indexer/factory.py
horsebox/indexer/index.py
horsebox/indexer/metadata.py
horsebox/indexer/schema.py
horsebox/indexer/analyzer/__init__.py
horsebox/indexer/analyzer/custom_analyzer_def.py
horsebox/indexer/analyzer/factory.py
horsebox/indexer/analyzer/filter_type.py
horsebox/indexer/analyzer/tokenizer_type.py
horsebox/model/__init__.py
horsebox/model/collector.py
horsebox/utils/__init__.py
horsebox/utils/batch.py
horsebox/utils/ipv6.py
horsebox/utils/normalize.py
horsebox/utils/stopword.py
horsebox/utils/strings.py
horsebox-0.10.0.dist-info/METADATA
horsebox-0.10.0.dist-info/WHEEL
horsebox-0.10.0.dist-info/entry_points.txt
horsebox-0.10.0.dist-info/licenses/LICENSE
horsebox-0.10.0.dist-info/RECORD
