Metadata-Version: 2.4
Name: horsebox
Version: 0.10.0
Summary: You Know, for local Search.
Project-URL: Homepage, https://github.com/michelcaradec/horsebox
Project-URL: Repository, https://github.com/michelcaradec/horsebox.git
Project-URL: Issues, https://github.com/michelcaradec/horsebox/issues
Project-URL: Changelog, https://github.com/michelcaradec/horsebox/blob/main/CHANGELOG.md
Author-email: Michel Caradec <mcaradec@proton.me>
Maintainer-email: Michel Caradec <mcaradec@proton.me>
License-Expression: MIT
License-File: LICENSE
Keywords: CLI,Search,Tantivy
Classifier: Development Status :: 5 - Production/Stable
Classifier: Environment :: Console
Classifier: Intended Audience :: Developers
Classifier: License :: OSI Approved :: MIT License
Classifier: Programming Language :: Python :: 3.9
Classifier: Programming Language :: Python :: 3.10
Classifier: Programming Language :: Python :: 3.11
Classifier: Programming Language :: Python :: 3.12
Classifier: Programming Language :: Python :: 3.13
Requires-Python: <3.14,>=3.9
Requires-Dist: click<8.2.0,>=8.1.8
Requires-Dist: feedparser>=6.0.11
Requires-Dist: ijson>=3.3.0
Requires-Dist: pdfminer-six>=20250506
Requires-Dist: tantivy==0.25.0
Requires-Dist: trafilatura>=2.0.0
Provides-Extra: dev
Requires-Dist: mypy>=1.16.1; extra == 'dev'
Requires-Dist: pre-commit>=4.2.0; extra == 'dev'
Requires-Dist: pytest>=8.4.1; extra == 'dev'
Requires-Dist: ruff; extra == 'dev'
Requires-Dist: tox>=4.27.0; extra == 'dev'
